collective.jsonmigrator-3.0.1-py3.10-nspkg.pth
collective/jsonmigrator/__init__.py
collective/jsonmigrator/configure.zcml
collective/jsonmigrator/helper.py
collective/jsonmigrator/testing.py
collective/jsonmigrator/blueprints/__init__.py
collective/jsonmigrator/blueprints/configure.zcml
collective/jsonmigrator/blueprints/datafields.py
collective/jsonmigrator/blueprints/local_roles.py
collective/jsonmigrator/blueprints/mimetype.py
collective/jsonmigrator/blueprints/order.py
collective/jsonmigrator/blueprints/owner.py
collective/jsonmigrator/blueprints/partialcommit.py
collective/jsonmigrator/blueprints/permissions.py
collective/jsonmigrator/blueprints/properties.py
collective/jsonmigrator/blueprints/skipitems.py
collective/jsonmigrator/blueprints/source_catalog.py
collective/jsonmigrator/blueprints/source_json.py
collective/jsonmigrator/blueprints/source_remote.py
collective/jsonmigrator/blueprints/statistics.py
collective/jsonmigrator/blueprints/translations.py
collective/jsonmigrator/blueprints/utils.py
collective/jsonmigrator/blueprints/workflowhistory.py
collective/jsonmigrator/pipelines/catalog.cfg
collective/jsonmigrator/pipelines/plone25.cfg
collective/jsonmigrator/tests/__init__.py
collective/jsonmigrator/tests/test_translations.py
collective/jsonmigrator/tests/test_utils.py
collective/jsonmigrator/tests/test_views.py
collective.jsonmigrator-3.0.1.dist-info/LICENSE.GPL
collective.jsonmigrator-3.0.1.dist-info/METADATA
collective.jsonmigrator-3.0.1.dist-info/WHEEL
collective.jsonmigrator-3.0.1.dist-info/entry_points.txt
collective.jsonmigrator-3.0.1.dist-info/namespace_packages.txt
collective.jsonmigrator-3.0.1.dist-info/top_level.txt
collective.jsonmigrator-3.0.1.dist-info/RECORD
