Metadata-Version: 2.1
Name: collective.jsonmigrator
Version: 3.0.1
Summary: Tool for you to migrate from old Plone sites
Home-page: https://github.com/collective/collective.jsonmigrator
Author: Rok Garbas
Author-email: rok@garbas.si
License: GPL version 2
Project-URL: PyPI, https://pypi.python.org/pypi/collective.jsonmigrator
Project-URL: Source, https://github.com/collective/collective.jsonmigrator
Project-URL: Tracker, https://github.com/collective/collective.jsonmigrator/issues
Keywords: plone transmogrifier plonecms migration
Classifier: Development Status :: 5 - Production/Stable
Classifier: Environment :: Web Environment
Classifier: Framework :: Plone :: 5.2
Classifier: Framework :: Plone :: 6.0
Classifier: Framework :: Plone :: Addon
Classifier: Framework :: Plone
Classifier: Framework :: Zope :: 4
Classifier: Framework :: Zope :: 5
Classifier: Intended Audience :: System Administrators
Classifier: License :: OSI Approved :: GNU General Public License (GPL)
Classifier: License :: OSI Approved :: GNU General Public License v2 (GPLv2)
Classifier: Operating System :: OS Independent
Classifier: Programming Language :: Python :: 3.7
Classifier: Programming Language :: Python :: 3.8
Classifier: Programming Language :: Python :: 3.9
Classifier: Programming Language :: Python
Classifier: Topic :: Software Development :: Libraries :: Python Modules
Requires-Python: >=3.7
License-File: LICENSE.GPL
Requires-Dist: collective.transmogrifier
Requires-Dist: plone.app.transmogrifier
Requires-Dist: Products.CMFPlone
Requires-Dist: setuptools
Requires-Dist: zope.interface
Provides-Extra: test
Requires-Dist: zope.testrunner ; extra == 'test'
Requires-Dist: plone.app.testing ; extra == 'test'
Requires-Dist: plone.uuid ; extra == 'test'
Requires-Dist: zope.component ; extra == 'test'
